sp_group.py
sp_pack.py
sprite_pipeline-0.3.0.dist-info/licenses/LICENSE
sprite_pipeline-0.3.0.dist-info/METADATA
sprite_pipeline-0.3.0.dist-info/WHEEL
sprite_pipeline-0.3.0.dist-info/entry_points.txt
sprite_pipeline-0.3.0.dist-info/top_level.txt
sprite_pipeline-0.3.0.dist-info/RECORD
