Metadata-Version: 2.4
Name: sprite-pipeline
Version: 0.3.0
Summary: A pipeline for converting images into stylized game sprites and sprite sheet generation.
Home-page: https://github.com/alexanderbrodko/sprite-pipeline
Author: Alexander Brodko
Classifier: Programming Language :: Python :: 3
Classifier: License :: OSI Approved :: GNU General Public License v3 (GPLv3)
Classifier: Operating System :: OS Independent
Requires-Python: >=3.8
License-File: LICENSE
Requires-Dist: numpy
Requires-Dist: opencv-python
Requires-Dist: torch
Requires-Dist: torchvision
Requires-Dist: modelscope
Requires-Dist: gdown
Requires-Dist: psd-tools
Requires-Dist: Pillow
Requires-Dist: tqdm
Requires-Dist: rectpack
Dynamic: author
Dynamic: classifier
Dynamic: description
Dynamic: description-content-type
Dynamic: home-page
Dynamic: license-file
Dynamic: requires-dist
Dynamic: requires-python
Dynamic: summary
